quickuse/__init__.py
quickuse/llms.py
quickuse/pandas_ai.py
quickuse/utils.py
quickuse/llamaindex/__init__.py
quickuse/llamaindex/queryengine.py
quickuse/llamaindex/reader.py
quickuse/tools/__init__.py
quickuse/tools/filetool.py
quickuse/tools/retools.py
quickuse/tools/small.py
quickuse-0.1.0.dist-info/METADATA
quickuse-0.1.0.dist-info/WHEEL
quickuse-0.1.0.dist-info/top_level.txt
quickuse-0.1.0.dist-info/RECORD
